genderclfml/__init__.py
genderclfml/genderclfml.py
genderclfml/models/gender_dTree_model.pkl
genderclfml/models/gender_logit_model.pkl
genderclfml/models/gender_nv_model.pkl
genderclfml/models/gender_vectorizer.pkl
genderclfml-0.1.0.dist-info/WHEEL
genderclfml-0.1.0.dist-info/METADATA
genderclfml-0.1.0.dist-info/RECORD
