Metadata-Version: 2.1
Name: genderclfml
Version: 0.1.0
Summary: Gender Classification for Names using Machine Learning
Author: Author
Requires-Python: >=3.9,<4.0
Classifier: Programming Language :: Python :: 3
Classifier: Programming Language :: Python :: 3.10
Classifier: Programming Language :: Python :: 3.9
Requires-Dist: joblib (>=1.1.0,<2.0.0)
Requires-Dist: scikit-learn (>=1.0.2,<2.0.0)
